{
	"id": "_common_basic_button_action_confirm",
	"name": "_common_basic_button_action_confirm",
	"spec": "1.0",
	"version": "1.0",
	"require": [
		{
			"type": "javascript",
			"src": "dojo/dojo.js",
			"$library": "dojo"
		},
		{
			"type": "javascript-module",
			"format": "amd",
			"src": "dijit/form/Button",
			"$library": "dojo"
		},
		{
			"type": "javascript-module",
			"format": "amd",
			"src": "_common_tooltipdialogconfirmation/_common_tooltipdialogconfirmation",
			"$library": "dojo"
		},
		{
			"$library": "dojo",
			"format": "amd",
			"src": "_common_basic_button_action_confirm/_common_basic_button_action_confirm",
			"type": "javascript-module"
		}
	],
	"library": {
		"dojo": {
			"src": "../../dojo/dojo/dojo.js"
		}
	},
	"content": "<div></div>"
}
